{"items": [{"productNumber": "000001", "productName": "3mm Timber Nails: 25 Count", "productTags": ["wood", "structure", "construction", "metal", "home", "fixing"], "variations": [{"variationID": "1", "variationName": "140mm", "variationCost": 3.8, "stockLevel": 120}, {"variationID": "2", "variationName": "160mm", "variationCost": 4.2, "stockLevel": 120}]}, {"productNumber": "000002", "productName": "3mm Masonry Nails: 26 Count", "productTags": ["brick", "masonry", "structure", "construction", "metal", "home", "fixing", "outdoor"], "variations": [{"variationID": "1", "variationName": "140mm", "variationCost": 4.2, "stockLevel": 84}]}, {"productNumber": "000003", "productName": "Drywall Plugs: 10 Pack", "productTags": ["dry", "wall", "screws", "mounting", "fastening"], "variations": [{"variationID": "1", "variationName": "5cm", "variationCost": "4.70", "stockLevel": "20"}, {"variationID": "2", "variationName": "10cm", "variationCost": 7.5, "stockLevel": 2}]}, {"productNumber": "000004", "productName": "Screw And Wall Plug Kit", "productTags": ["mounting", "hardware", "fixing"], "variations": [{"variationID": "1", "variationName": "280 Piece", "variationCost": 10.6, "stockLevel": 60}]}, {"productNumber": "000005", "productName": "Matt Emulsion 10L", "productTags": ["paint", "interior", "home", "office", "walls", "matte", "indoor"], "variations": [{"variationID": "1", "variationName": "Rose Pink", "variationCost": 15.5, "stockLevel": 50}]}, {"productNumber": "000006", "productName": "MacDonald's Wood Stain", "productTags": ["wood", "outdoor", "indoor", "home", "varnish"], "variations": [{"variationID": "1", "variationName": "Ebony 5L", "variationCost": 8.6, "stockLevel": 8}]}, {"productNumber": "000007", "productName": "Whitewood Planed Square Edge Timber", "productTags": ["oak", "birch", "pse", "construction", "wood"], "variations": [{"variationID": "1", "variationName": "18x44x2400mm", "variationCost": 5.8, "stockLevel": 54}]}, {"productNumber": "000008", "productName": "MacDonald Leaf Blower", "productTags": ["outdoor", "garden", "gardening"], "variations": [{"variationID": "1", "variationName": "Orange", "variationCost": 120, "stockLevel": 0}]}, {"productNumber": "000009", "productName": "Copper Pipe: 25mm Diameter", "productTags": ["copper", "plumbing", "heating", "water"], "variations": [{"variationID": "1", "variationName": "5m", "variationCost": 10, "stockLevel": 56}]}, {"productNumber": "000010", "productName": "Plastic Pipe: 25mm Diameter", "productTags": ["plastic", "plumbing", "heating", "water"], "variations": [{"variationID": "1", "variationName": "5m", "variationCost": 7.5, "stockLevel": 4}]}]}